{"paragraphs":[{"text":"%md\n## WORKSHOP SOLUTION NOTEBOOK\n","user":"admin","dateUpdated":"2019-07-28T07:25:37+0800","config":{"tableHide":false,"editorSetting":{"language":"markdown","editOnDblClick":true,"completionSupport":false},"colWidth":12,"editorMode":"ace/mode/markdown","fontSize":9,"editorHide":true,"results":{},"enabled":true},"settings":{"params":{},"forms":{}},"results":{"code":"SUCCESS","msg":[{"type":"HTML","data":"<h2>WORKSHOP SOLUTION NOTEBOOK</h2>\n"}]},"apps":[],"jobName":"paragraph_1564269838500_208773155","id":"20190727-101445_277139120","dateCreated":"2019-07-28T07:23:58+0800","dateStarted":"2019-07-28T07:25:37+0800","dateFinished":"2019-07-28T07:25:39+0800","status":"FINISHED","progressUpdateIntervalMs":500,"focus":true,"$$hashKey":"object:304"},{"text":"%md\n#### HDFS Commands","user":"admin","dateUpdated":"2019-07-28T07:25:40+0800","config":{"tableHide":false,"editorSetting":{"language":"markdown","editOnDblClick":true,"completionSupport":false},"colWidth":12,"editorMode":"ace/mode/markdown","fontSize":9,"editorHide":true,"results":{},"enabled":true},"settings":{"params":{},"forms":{}},"results":{"code":"SUCCESS","msg":[{"type":"HTML","data":"<h4>HDFS Commands</h4>\n"}]},"apps":[],"jobName":"paragraph_1564269838504_-297052278","id":"20190727-101507_1726448364","dateCreated":"2019-07-28T07:23:58+0800","dateStarted":"2019-07-28T07:25:40+0800","dateFinished":"2019-07-28T07:25:40+0800","status":"FINISHED","progressUpdateIntervalMs":500,"$$hashKey":"object:305"},{"text":"%sh\nhdfs dfs -ls /workshop/clickstream/data/raw","user":"admin","dateUpdated":"2019-07-29T08:09:42+0800","config":{"tableHide":false,"editorSetting":{"language":"sh","editOnDblClick":false,"completionSupport":false},"colWidth":12,"editorMode":"ace/mode/sh","fontSize":9,"editorHide":false,"results":{},"enabled":true},"settings":{"params":{},"forms":{}},"results":{"code":"SUCCESS","msg":[{"type":"TEXT","data":"Found 1 items\n-rw-r--r--   1 admin hdfs   67987881 2019-07-28 08:19 /workshop/clickstream/data/raw/filtered-omniture-raw.tsv\n"}]},"apps":[],"jobName":"paragraph_1564269838505_-920717267","id":"20190727-095750_1465186959","dateCreated":"2019-07-28T07:23:58+0800","dateStarted":"2019-07-29T08:09:42+0800","dateFinished":"2019-07-29T08:09:46+0800","status":"FINISHED","progressUpdateIntervalMs":500,"$$hashKey":"object:306"},{"text":"%md\n#### Create WORKSHOP Database\n","user":"admin","dateUpdated":"2019-07-29T08:10:00+0800","config":{"tableHide":false,"editorSetting":{"language":"markdown","editOnDblClick":true,"completionSupport":false},"colWidth":12,"editorMode":"ace/mode/markdown","fontSize":9,"editorHide":true,"results":{},"enabled":true},"settings":{"params":{},"forms":{}},"results":{"code":"SUCCESS","msg":[{"type":"HTML","data":"<h4>Create WORKSHOP Database</h4>\n"}]},"apps":[],"jobName":"paragraph_1564269838505_1336886169","id":"20190727-101520_557945496","dateCreated":"2019-07-28T07:23:58+0800","status":"FINISHED","progressUpdateIntervalMs":500,"$$hashKey":"object:308","dateFinished":"2019-07-29T08:10:02+0800","dateStarted":"2019-07-29T08:10:00+0800"},{"text":"CREATE DATABASE IF NOT EXISTS WORKSHOP","user":"admin","dateUpdated":"2019-07-29T08:11:36+0800","config":{"tableHide":false,"editorSetting":{"language":"sql","editOnDblClick":false,"completionSupport":true,"completionKey":"TAB"},"colWidth":12,"editorMode":"ace/mode/sql","fontSize":9,"editorHide":false,"results":{},"enabled":true},"settings":{"params":{},"forms":{}},"results":{"code":"SUCCESS","msg":[{"type":"TEXT","data":"Query executed successfully. Affected rows : -1"}]},"apps":[],"jobName":"paragraph_1564269838505_-769139325","id":"20190727-095616_1674723443","dateCreated":"2019-07-28T07:23:58+0800","status":"FINISHED","progressUpdateIntervalMs":500,"$$hashKey":"object:309","dateFinished":"2019-07-29T08:11:41+0800","dateStarted":"2019-07-29T08:11:36+0800"},{"text":"use workshop\n","user":"admin","dateUpdated":"2019-07-29T08:14:01+0800","config":{"tableHide":true,"editorSetting":{"language":"sql","editOnDblClick":false,"completionKey":"TAB","completionSupport":true},"colWidth":12,"editorMode":"ace/mode/sql","fontSize":9,"editorHide":false,"results":{"0":{"graph":{"mode":"table","height":300,"optionOpen":false,"setting":{"table":{"tableGridState":{},"tableColumnTypeState":{"names":{"tab_name":"string"},"updated":false},"tableOptionSpecHash":"[{\"name\":\"useFilter\",\"valueType\":\"boolean\",\"defaultValue\":false,\"widget\":\"checkbox\",\"description\":\"Enable filter for columns\"},{\"name\":\"showPagination\",\"valueType\":\"boolean\",\"defaultValue\":false,\"widget\":\"checkbox\",\"description\":\"Enable pagination for better navigation\"},{\"name\":\"showAggregationFooter\",\"valueType\":\"boolean\",\"defaultValue\":false,\"widget\":\"checkbox\",\"description\":\"Enable a footer for displaying aggregated values\"}]","tableOptionValue":{"useFilter":false,"showPagination":false,"showAggregationFooter":false},"updated":false,"initialized":false}},"commonSetting":{}}}},"enabled":true},"settings":{"params":{},"forms":{}},"results":{"code":"SUCCESS","msg":[{"type":"TEXT","data":"Query executed successfully. Affected rows : -1"}]},"apps":[],"jobName":"paragraph_1564269838506_-2107504498","id":"20190727-095408_1490086546","dateCreated":"2019-07-28T07:23:58+0800","status":"FINISHED","progressUpdateIntervalMs":500,"$$hashKey":"object:310","dateFinished":"2019-07-29T08:14:02+0800","dateStarted":"2019-07-29T08:14:01+0800"},{"text":"show tables","user":"admin","dateUpdated":"2019-07-29T08:14:11+0800","config":{"tableHide":false,"editorSetting":{"language":"sql","editOnDblClick":false,"completionSupport":true,"completionKey":"TAB"},"colWidth":12,"editorMode":"ace/mode/sql","fontSize":9,"editorHide":false,"results":{"0":{"graph":{"mode":"table","height":300,"optionOpen":false,"setting":{"table":{"tableGridState":{},"tableColumnTypeState":{"names":{"tab_name":"string"},"updated":false},"tableOptionSpecHash":"[{\"name\":\"useFilter\",\"valueType\":\"boolean\",\"defaultValue\":false,\"widget\":\"checkbox\",\"description\":\"Enable filter for columns\"},{\"name\":\"showPagination\",\"valueType\":\"boolean\",\"defaultValue\":false,\"widget\":\"checkbox\",\"description\":\"Enable pagination for better navigation\"},{\"name\":\"showAggregationFooter\",\"valueType\":\"boolean\",\"defaultValue\":false,\"widget\":\"checkbox\",\"description\":\"Enable a footer for displaying aggregated values\"}]","tableOptionValue":{"useFilter":false,"showPagination":false,"showAggregationFooter":false},"updated":false,"initialized":false}},"commonSetting":{}}}},"enabled":true},"settings":{"params":{},"forms":{}},"results":{"code":"SUCCESS","msg":[{"type":"TABLE","data":"tab_name\n"}]},"apps":[],"jobName":"paragraph_1564269838506_-1366746628","id":"20190727-095539_1054754543","dateCreated":"2019-07-28T07:23:58+0800","status":"FINISHED","progressUpdateIntervalMs":500,"$$hashKey":"object:311","dateFinished":"2019-07-29T08:14:08+0800","dateStarted":"2019-07-29T08:14:08+0800"},{"text":"%md\n#### USERS - External and Internal tables","user":"admin","dateUpdated":"2019-07-29T08:14:16+0800","config":{"tableHide":false,"editorSetting":{"language":"markdown","editOnDblClick":true,"completionSupport":false},"colWidth":12,"editorMode":"ace/mode/markdown","fontSize":9,"editorHide":true,"results":{},"enabled":true},"settings":{"params":{},"forms":{}},"results":{"code":"SUCCESS","msg":[{"type":"HTML","data":"<h4>USERS - External and Internal tables</h4>\n"}]},"apps":[],"jobName":"paragraph_1564269838506_-1234224171","id":"20190727-101556_378586941","dateCreated":"2019-07-28T07:23:58+0800","status":"FINISHED","progressUpdateIntervalMs":500,"$$hashKey":"object:312","dateFinished":"2019-07-29T08:14:16+0800","dateStarted":"2019-07-29T08:14:16+0800"},{"text":"DROP TABLE IF EXISTS USERS","user":"admin","dateUpdated":"2019-07-29T08:14:18+0800","config":{"tableHide":true,"editorSetting":{"language":"sql","editOnDblClick":false,"completionSupport":true,"completionKey":"TAB"},"colWidth":12,"editorMode":"ace/mode/sql","fontSize":9,"editorHide":false,"results":{},"enabled":true},"settings":{"params":{},"forms":{}},"results":{"code":"SUCCESS","msg":[{"type":"TEXT","data":"Query executed successfully. Affected rows : -1"}]},"apps":[],"jobName":"paragraph_1564269838506_1629975550","id":"20190727-095429_2092897628","dateCreated":"2019-07-28T07:23:58+0800","status":"FINISHED","progressUpdateIntervalMs":500,"$$hashKey":"object:313","dateFinished":"2019-07-29T08:14:19+0800","dateStarted":"2019-07-29T08:14:18+0800"},{"text":"CREATE EXTERNAL TABLE IF NOT EXISTS USERS \n(SWID STRING, BIRTH_DT STRING, GENDER_CD STRING) \nROW FORMAT DELIMITED FIELDS TERMINATED BY '\\t' STORED AS TEXTFILE \nLOCATION \"/workshop/clickstream/data/users\"","user":"admin","dateUpdated":"2019-07-29T08:14:24+0800","config":{"tableHide":true,"editorSetting":{"language":"sql","editOnDblClick":false,"completionSupport":true,"completionKey":"TAB"},"colWidth":12,"editorMode":"ace/mode/sql","fontSize":9,"editorHide":false,"results":{},"enabled":true},"settings":{"params":{},"forms":{}},"results":{"code":"SUCCESS","msg":[{"type":"TEXT","data":"Query executed successfully. Affected rows : -1"}]},"apps":[],"jobName":"paragraph_1564269838507_1630265248","id":"20190727-095654_864337887","dateCreated":"2019-07-28T07:23:58+0800","status":"FINISHED","progressUpdateIntervalMs":500,"$$hashKey":"object:314","dateFinished":"2019-07-29T08:14:24+0800","dateStarted":"2019-07-29T08:14:24+0800"},{"text":"SELECT * FROM USERS LIMIT 10","user":"admin","dateUpdated":"2019-07-29T08:14:32+0800","config":{"tableHide":false,"editorSetting":{"language":"sql","editOnDblClick":false,"completionSupport":true,"completionKey":"TAB"},"colWidth":12,"editorMode":"ace/mode/sql","fontSize":9,"editorHide":false,"results":{"0":{"graph":{"mode":"table","height":300,"optionOpen":false,"setting":{"table":{"tableGridState":{},"tableColumnTypeState":{"names":{"users.swid":"string","users.birth_dt":"string","users.gender_cd":"string"},"updated":false},"tableOptionSpecHash":"[{\"name\":\"useFilter\",\"valueType\":\"boolean\",\"defaultValue\":false,\"widget\":\"checkbox\",\"description\":\"Enable filter for columns\"},{\"name\":\"showPagination\",\"valueType\":\"boolean\",\"defaultValue\":false,\"widget\":\"checkbox\",\"description\":\"Enable pagination for better navigation\"},{\"name\":\"showAggregationFooter\",\"valueType\":\"boolean\",\"defaultValue\":false,\"widget\":\"checkbox\",\"description\":\"Enable a footer for displaying aggregated values\"}]","tableOptionValue":{"useFilter":false,"showPagination":false,"showAggregationFooter":false},"updated":false,"initialized":false}},"commonSetting":{}}}},"enabled":true},"settings":{"params":{},"forms":{}},"results":{"code":"SUCCESS","msg":[{"type":"TABLE","data":"users.swid\tusers.birth_dt\tusers.gender_cd\nSWID\tBIRTH_DT\tGENDER_CD\n0001BDD9-EABF-4D0D-81BD-D9EABFCD0D7D\t4/8/84\tF\n00071AA7-86D2-4EB9-871A-A786D27EB9BA\t2/7/88\tF\n00071B7D-31AF-4D85-871B-7D31AFFD852E\t10/22/64\tF\n0007967E-F188-4598-9C7C-E64390482CFB\t6/1/66\tM\n000B90B2-92DC-4A7A-8B90-B292DC9A7A71\t6/13/84\tM\n000C1856-994E-476B-8C18-56994E676B29\t12/29/80\tU\n000F36E5-9891-4098-9B69-CEE78483B653\t3/24/85\tF\n00102F3F-061C-4212-9F91-1254F9D6E39F\t11/1/91\tF\n0010C6F2-8C04-450E-90C6-F28C04B50E97\t6/20/02\tU\n"}]},"apps":[],"jobName":"paragraph_1564269838507_1987928962","id":"20190727-095704_448630835","dateCreated":"2019-07-28T07:23:58+0800","status":"FINISHED","progressUpdateIntervalMs":500,"$$hashKey":"object:315","dateFinished":"2019-07-29T08:14:30+0800","dateStarted":"2019-07-29T08:14:28+0800"},{"text":"DROP TABLE IF EXISTS USERS_ORC","user":"admin","dateUpdated":"2019-07-29T08:14:41+0800","config":{"tableHide":false,"editorSetting":{"language":"sql","editOnDblClick":false,"completionSupport":true,"completionKey":"TAB"},"colWidth":12,"editorMode":"ace/mode/sql","fontSize":9,"editorHide":false,"results":{},"enabled":true},"settings":{"params":{},"forms":{}},"results":{"code":"SUCCESS","msg":[{"type":"TEXT","data":"Query executed successfully. Affected rows : -1"}]},"apps":[],"jobName":"paragraph_1564269838507_1054060921","id":"20190727-095718_857874277","dateCreated":"2019-07-28T07:23:58+0800","status":"FINISHED","progressUpdateIntervalMs":500,"$$hashKey":"object:316","dateFinished":"2019-07-29T08:14:38+0800","dateStarted":"2019-07-29T08:14:37+0800"},{"text":"CREATE TABLE IF NOT EXISTS USERS_ORC AS\nSELECT * FROM USERS","user":"admin","dateUpdated":"2019-07-29T08:14:51+0800","config":{"tableHide":false,"editorSetting":{"language":"sql","editOnDblClick":false,"completionSupport":true,"completionKey":"TAB"},"colWidth":12,"editorMode":"ace/mode/sql","fontSize":9,"editorHide":false,"results":{},"enabled":true},"settings":{"params":{},"forms":{}},"results":{"code":"SUCCESS","msg":[{"type":"TEXT","data":"Query executed successfully. Affected rows : -1"}]},"apps":[],"jobName":"paragraph_1564269838507_-165730854","id":"20190727-100111_1879188537","dateCreated":"2019-07-28T07:23:58+0800","status":"FINISHED","progressUpdateIntervalMs":500,"$$hashKey":"object:317","dateFinished":"2019-07-29T08:14:49+0800","dateStarted":"2019-07-29T08:14:45+0800"},{"text":"SELECT * FROM USERS_ORC LIMIT 10","user":"admin","dateUpdated":"2019-07-29T08:14:58+0800","config":{"tableHide":false,"editorSetting":{"language":"sql","editOnDblClick":false,"completionSupport":true,"completionKey":"TAB"},"colWidth":12,"editorMode":"ace/mode/sql","fontSize":9,"editorHide":false,"results":{"0":{"graph":{"mode":"table","height":300,"optionOpen":false,"setting":{"table":{"tableGridState":{},"tableColumnTypeState":{"names":{"users_orc.swid":"string","users_orc.birth_dt":"string","users_orc.gender_cd":"string"},"updated":false},"tableOptionSpecHash":"[{\"name\":\"useFilter\",\"valueType\":\"boolean\",\"defaultValue\":false,\"widget\":\"checkbox\",\"description\":\"Enable filter for columns\"},{\"name\":\"showPagination\",\"valueType\":\"boolean\",\"defaultValue\":false,\"widget\":\"checkbox\",\"description\":\"Enable pagination for better navigation\"},{\"name\":\"showAggregationFooter\",\"valueType\":\"boolean\",\"defaultValue\":false,\"widget\":\"checkbox\",\"description\":\"Enable a footer for displaying aggregated values\"}]","tableOptionValue":{"useFilter":false,"showPagination":false,"showAggregationFooter":false},"updated":false,"initialized":false}},"commonSetting":{}}}},"enabled":true},"settings":{"params":{},"forms":{}},"results":{"code":"SUCCESS","msg":[{"type":"TABLE","data":"users_orc.swid\tusers_orc.birth_dt\tusers_orc.gender_cd\nSWID\tBIRTH_DT\tGENDER_CD\n0001BDD9-EABF-4D0D-81BD-D9EABFCD0D7D\t4/8/84\tF\n00071AA7-86D2-4EB9-871A-A786D27EB9BA\t2/7/88\tF\n00071B7D-31AF-4D85-871B-7D31AFFD852E\t10/22/64\tF\n0007967E-F188-4598-9C7C-E64390482CFB\t6/1/66\tM\n000B90B2-92DC-4A7A-8B90-B292DC9A7A71\t6/13/84\tM\n000C1856-994E-476B-8C18-56994E676B29\t12/29/80\tU\n000F36E5-9891-4098-9B69-CEE78483B653\t3/24/85\tF\n00102F3F-061C-4212-9F91-1254F9D6E39F\t11/1/91\tF\n0010C6F2-8C04-450E-90C6-F28C04B50E97\t6/20/02\tU\n"}]},"apps":[],"jobName":"paragraph_1564269838508_838904141","id":"20190727-100217_1379626738","dateCreated":"2019-07-28T07:23:58+0800","status":"FINISHED","progressUpdateIntervalMs":500,"$$hashKey":"object:318","dateFinished":"2019-07-29T08:14:56+0800","dateStarted":"2019-07-29T08:14:56+0800"},{"text":"DROP TABLE IF EXISTS PRODUCTS","user":"admin","dateUpdated":"2019-07-29T08:15:03+0800","config":{"tableHide":true,"editorSetting":{"language":"sql","editOnDblClick":false,"completionSupport":true,"completionKey":"TAB"},"colWidth":12,"editorMode":"ace/mode/sql","fontSize":9,"editorHide":false,"results":{},"enabled":true},"settings":{"params":{},"forms":{}},"results":{"code":"SUCCESS","msg":[{"type":"TEXT","data":"Query executed successfully. Affected rows : -1"}]},"apps":[],"jobName":"paragraph_1564269838508_415125219","id":"20190727-100227_994373023","dateCreated":"2019-07-28T07:23:58+0800","status":"FINISHED","progressUpdateIntervalMs":500,"$$hashKey":"object:319","dateFinished":"2019-07-29T08:15:03+0800","dateStarted":"2019-07-29T08:15:03+0800"},{"text":"%md\n#### PRODUCTS - External and Internal Tables","user":"admin","dateUpdated":"2019-07-29T08:15:10+0800","config":{"tableHide":false,"editorSetting":{"language":"markdown","editOnDblClick":true,"completionSupport":false},"colWidth":12,"editorMode":"ace/mode/markdown","fontSize":9,"editorHide":true,"results":{},"enabled":true},"settings":{"params":{},"forms":{}},"results":{"code":"SUCCESS","msg":[{"type":"HTML","data":"<h4>PRODUCTS - External and Internal Tables</h4>\n"}]},"apps":[],"jobName":"paragraph_1564269838508_-512539093","id":"20190727-101218_1809932778","dateCreated":"2019-07-28T07:23:58+0800","status":"FINISHED","progressUpdateIntervalMs":500,"$$hashKey":"object:320","dateFinished":"2019-07-29T08:15:10+0800","dateStarted":"2019-07-29T08:15:10+0800"},{"text":"CREATE EXTERNAL TABLE IF NOT EXISTS PRODUCTS\n(URL STRING, CATEGORY STRING, DESCRIPTION STRING) \nROW FORMAT DELIMITED FIELDS TERMINATED BY '\\t' STORED AS TEXTFILE \nLOCATION \"/workshop/clickstream/data/products\"","user":"admin","dateUpdated":"2019-07-29T08:15:35+0800","config":{"tableHide":true,"editorSetting":{"language":"sql","editOnDblClick":false,"completionSupport":true,"completionKey":"TAB"},"colWidth":12,"editorMode":"ace/mode/sql","fontSize":9,"editorHide":false,"results":{},"enabled":true},"settings":{"params":{},"forms":{}},"results":{"code":"SUCCESS","msg":[{"type":"TEXT","data":"Query executed successfully. Affected rows : -1"}]},"apps":[],"jobName":"paragraph_1564269838508_-1472503639","id":"20190727-100729_1565761642","dateCreated":"2019-07-28T07:23:58+0800","status":"FINISHED","progressUpdateIntervalMs":500,"$$hashKey":"object:321","dateFinished":"2019-07-29T08:15:35+0800","dateStarted":"2019-07-29T08:15:35+0800"},{"text":"SELECT * FROM PRODUCTS LIMIT 10","user":"admin","dateUpdated":"2019-07-29T08:15:40+0800","config":{"tableHide":false,"editorSetting":{"language":"sql","editOnDblClick":false,"completionSupport":true,"completionKey":"TAB"},"colWidth":12,"editorMode":"ace/mode/sql","fontSize":9,"editorHide":false,"results":{"0":{"graph":{"mode":"table","height":300,"optionOpen":false,"setting":{"table":{"tableGridState":{},"tableColumnTypeState":{"names":{"products.url":"string","products.category":"string","products.description":"string"},"updated":false},"tableOptionSpecHash":"[{\"name\":\"useFilter\",\"valueType\":\"boolean\",\"defaultValue\":false,\"widget\":\"checkbox\",\"description\":\"Enable filter for columns\"},{\"name\":\"showPagination\",\"valueType\":\"boolean\",\"defaultValue\":false,\"widget\":\"checkbox\",\"description\":\"Enable pagination for better navigation\"},{\"name\":\"showAggregationFooter\",\"valueType\":\"boolean\",\"defaultValue\":false,\"widget\":\"checkbox\",\"description\":\"Enable a footer for displaying aggregated values\"}]","tableOptionValue":{"useFilter":false,"showPagination":false,"showAggregationFooter":false},"updated":false,"initialized":false}},"commonSetting":{}}}},"enabled":true},"settings":{"params":{},"forms":{}},"results":{"code":"SUCCESS","msg":[{"type":"TABLE","data":"products.url\tproducts.category\tproducts.description\n/\tHome Page\tHome Page\n/SH55126545/VD55149415\tChecking-Account\tChecking Account\n/SH55126545/VD55163347\tSavings-Account\tSavings Account\n/SH55126545/VD55165149\tMoney-Market\tMoney Market Account\n/SH55126545/VD55166807\tMortgage-30YR-Fixed\t30 Year Mortgage Loan\n/SH55126545/VD55170364\tMortgage-15YR-Fixed\t15 Year Mortgage Loan\n/SH5580165/VD55156528\tMortgage-10YR-Fixed\t10 Year Mortgage Loan\n/SH5580165/VD55173281\tVISA-Debit\tVISA Debit Card\n/SH5582037/VD5582082\tIRA\tIRA Savings\n/SH5584743/VD55178549\tHome_Equity_1\t\"Home Equity Loan under $20,000\"\n"}]},"apps":[],"jobName":"paragraph_1564269838509_844446819","id":"20190727-100743_974493337","dateCreated":"2019-07-28T07:23:58+0800","status":"FINISHED","progressUpdateIntervalMs":500,"$$hashKey":"object:322","dateFinished":"2019-07-29T08:15:41+0800","dateStarted":"2019-07-29T08:15:40+0800"},{"text":"DROP TABLE IF EXISTS PRODUCTS_ORC","user":"admin","dateUpdated":"2019-07-29T08:15:50+0800","config":{"tableHide":true,"editorSetting":{"language":"sql","editOnDblClick":false,"completionSupport":true,"completionKey":"TAB"},"colWidth":12,"editorMode":"ace/mode/sql","fontSize":9,"editorHide":false,"results":{},"enabled":true},"settings":{"params":{},"forms":{}},"results":{"code":"SUCCESS","msg":[{"type":"TEXT","data":"Query executed successfully. Affected rows : -1"}]},"apps":[],"jobName":"paragraph_1564269838509_-186325537","id":"20190727-100753_1760951336","dateCreated":"2019-07-28T07:23:58+0800","status":"FINISHED","progressUpdateIntervalMs":500,"$$hashKey":"object:323","dateFinished":"2019-07-29T08:15:50+0800","dateStarted":"2019-07-29T08:15:50+0800"},{"text":"CREATE TABLE IF NOT EXISTS PRODUCTS_ORC AS\nSELECT * FROM PRODUCTS","user":"admin","dateUpdated":"2019-07-29T08:15:52+0800","config":{"tableHide":true,"editorSetting":{"language":"sql","editOnDblClick":false,"completionSupport":true,"completionKey":"TAB"},"colWidth":12,"editorMode":"ace/mode/sql","fontSize":9,"editorHide":false,"results":{},"enabled":true},"settings":{"params":{},"forms":{}},"results":{"code":"SUCCESS","msg":[{"type":"TEXT","data":"Query executed successfully. Affected rows : -1"}]},"apps":[],"jobName":"paragraph_1564269838509_-922505598","id":"20190727-100842_1580521238","dateCreated":"2019-07-28T07:23:58+0800","status":"FINISHED","progressUpdateIntervalMs":500,"$$hashKey":"object:324","dateFinished":"2019-07-29T08:15:53+0800","dateStarted":"2019-07-29T08:15:52+0800"},{"text":"SELECT * FROM PRODUCTS_ORC LIMIT 10","user":"admin","dateUpdated":"2019-07-29T08:16:04+0800","config":{"tableHide":false,"editorSetting":{"language":"sql","editOnDblClick":false,"completionSupport":true,"completionKey":"TAB"},"colWidth":12,"editorMode":"ace/mode/sql","fontSize":9,"editorHide":false,"results":{"0":{"graph":{"mode":"table","height":300,"optionOpen":false,"setting":{"table":{"tableGridState":{},"tableColumnTypeState":{"names":{"products_orc.url":"string","products_orc.category":"string","products_orc.description":"string"},"updated":false},"tableOptionSpecHash":"[{\"name\":\"useFilter\",\"valueType\":\"boolean\",\"defaultValue\":false,\"widget\":\"checkbox\",\"description\":\"Enable filter for columns\"},{\"name\":\"showPagination\",\"valueType\":\"boolean\",\"defaultValue\":false,\"widget\":\"checkbox\",\"description\":\"Enable pagination for better navigation\"},{\"name\":\"showAggregationFooter\",\"valueType\":\"boolean\",\"defaultValue\":false,\"widget\":\"checkbox\",\"description\":\"Enable a footer for displaying aggregated values\"}]","tableOptionValue":{"useFilter":false,"showPagination":false,"showAggregationFooter":false},"updated":false,"initialized":false}},"commonSetting":{}}}},"enabled":true},"settings":{"params":{},"forms":{}},"results":{"code":"SUCCESS","msg":[{"type":"TABLE","data":"products_orc.url\tproducts_orc.category\tproducts_orc.description\n/\tHome Page\tHome Page\n/SH55126545/VD55149415\tChecking-Account\tChecking Account\n/SH55126545/VD55163347\tSavings-Account\tSavings Account\n/SH55126545/VD55165149\tMoney-Market\tMoney Market Account\n/SH55126545/VD55166807\tMortgage-30YR-Fixed\t30 Year Mortgage Loan\n/SH55126545/VD55170364\tMortgage-15YR-Fixed\t15 Year Mortgage Loan\n/SH5580165/VD55156528\tMortgage-10YR-Fixed\t10 Year Mortgage Loan\n/SH5580165/VD55173281\tVISA-Debit\tVISA Debit Card\n/SH5582037/VD5582082\tIRA\tIRA Savings\n/SH5584743/VD55178549\tHome_Equity_1\t\"Home Equity Loan under $20,000\"\n"}]},"apps":[],"jobName":"paragraph_1564269838509_-1274643469","id":"20190727-100854_1480052520","dateCreated":"2019-07-28T07:23:58+0800","status":"FINISHED","progressUpdateIntervalMs":500,"$$hashKey":"object:325","dateFinished":"2019-07-29T08:16:04+0800","dateStarted":"2019-07-29T08:16:04+0800"},{"text":"%md\n#### clickstream_events from Kafka Topic ingested into Druid using Hive External Table with Druid Storage Handler","user":"admin","dateUpdated":"2019-07-29T08:16:10+0800","config":{"tableHide":false,"editorSetting":{"language":"markdown","editOnDblClick":true,"completionSupport":false},"colWidth":12,"editorMode":"ace/mode/markdown","fontSize":9,"editorHide":true,"results":{},"enabled":true},"settings":{"params":{},"forms":{}},"results":{"code":"SUCCESS","msg":[{"type":"HTML","data":"<h4>clickstream_events from Kafka Topic ingested into Druid using Hive External Table with Druid Storage Handler</h4>\n"}]},"apps":[],"jobName":"paragraph_1564269838509_489927945","id":"20190727-101121_1746811176","dateCreated":"2019-07-28T07:23:58+0800","status":"FINISHED","progressUpdateIntervalMs":500,"$$hashKey":"object:326","dateFinished":"2019-07-29T08:16:10+0800","dateStarted":"2019-07-29T08:16:10+0800"},{"text":"DROP TABLE IF EXISTS CLICKSTREAM_EVENTS","user":"admin","dateUpdated":"2019-07-29T08:54:04+0800","config":{"tableHide":true,"editorSetting":{"language":"sql","editOnDblClick":false,"completionSupport":true,"completionKey":"TAB"},"colWidth":12,"editorMode":"ace/mode/sql","fontSize":9,"editorHide":false,"results":{},"enabled":true},"settings":{"params":{},"forms":{}},"apps":[],"jobName":"paragraph_1564269838510_-1404517230","id":"20190727-101249_208764805","dateCreated":"2019-07-28T07:23:58+0800","status":"FINISHED","progressUpdateIntervalMs":500,"$$hashKey":"object:327","dateFinished":"2019-07-29T08:54:04+0800","dateStarted":"2019-07-29T08:54:04+0800","results":{"code":"SUCCESS","msg":[{"type":"TEXT","data":"Query executed successfully. Affected rows : -1"}]}},{"text":"CREATE EXTERNAL TABLE workshop.clickstream_events (\n`__time` timestamp,\nclickstream_id string,\nuser_session_id string,\nipaddress string,\nts string,\ngender string,\nbday string,\nis_purchased string,\nis_page_errored string,\nurl string,\ncity string,\nstate string,\ncountry string\n)\nSTORED BY 'org.apache.hadoop.hive.druid.DruidStorageHandler'\nTBLPROPERTIES (\n\"kafka.bootstrap.servers\" = \"demo.cloudera.com:6667\",\n\"kafka.topic\" = \"clickstream_events\",\n\"druid.kafka.ingestion.useEarliestOffset\" = \"true\",\n\"druid.kafka.ingestion.maxRowsInMemory\" = \"5\",\n\"druid.kafka.ingestion.startDelay\" = \"PT1S\",\n\"druid.kafka.ingestion.period\" = \"PT1S\",\n\"druid.kafka.ingestion.consumer.retries\" = \"2\"\n)","user":"admin","dateUpdated":"2019-07-29T08:54:07+0800","config":{"tableHide":false,"editorSetting":{"language":"sql","editOnDblClick":false,"completionSupport":true,"completionKey":"TAB"},"colWidth":12,"editorMode":"ace/mode/sql","fontSize":9,"editorHide":false,"results":{},"enabled":true},"settings":{"params":{},"forms":{}},"apps":[],"jobName":"paragraph_1564269838510_1242983630","id":"20190727-100902_848430795","dateCreated":"2019-07-28T07:23:58+0800","status":"FINISHED","progressUpdateIntervalMs":500,"$$hashKey":"object:328","dateFinished":"2019-07-29T08:54:08+0800","dateStarted":"2019-07-29T08:54:07+0800","results":{"code":"SUCCESS","msg":[{"type":"TEXT","data":"Query executed successfully. Affected rows : -1"}]}},{"text":"%md\n**Start Druid Ingestion**","user":"admin","dateUpdated":"2019-07-29T08:18:58+0800","config":{"tableHide":false,"editorSetting":{"language":"markdown","editOnDblClick":true,"completionSupport":false},"colWidth":12,"editorMode":"ace/mode/markdown","fontSize":9,"editorHide":true,"results":{},"enabled":true},"settings":{"params":{},"forms":{}},"results":{"code":"SUCCESS","msg":[{"type":"HTML","data":"<p><strong>Start Druid Ingestion</strong></p>\n"}]},"apps":[],"jobName":"paragraph_1564269838510_-1783860228","id":"20190727-101057_1915909759","dateCreated":"2019-07-28T07:23:58+0800","status":"FINISHED","progressUpdateIntervalMs":500,"$$hashKey":"object:329","dateFinished":"2019-07-29T08:18:58+0800","dateStarted":"2019-07-29T08:18:58+0800"},{"text":"ALTER TABLE workshop.clickstream_events SET TBLPROPERTIES('druid.kafka.ingestion' = 'START')\n","user":"admin","dateUpdated":"2019-07-29T08:54:13+0800","config":{"tableHide":false,"editorSetting":{"language":"sql","editOnDblClick":false,"completionSupport":true,"completionKey":"TAB"},"colWidth":12,"editorMode":"ace/mode/sql","fontSize":9,"editorHide":false,"results":{},"enabled":true},"settings":{"params":{},"forms":{}},"results":{"code":"SUCCESS","msg":[{"type":"TEXT","data":"Query executed successfully. Affected rows : -1"}]},"apps":[],"jobName":"paragraph_1564269838510_790329153","id":"20190727-101922_1910603729","dateCreated":"2019-07-28T07:23:58+0800","status":"FINISHED","progressUpdateIntervalMs":500,"$$hashKey":"object:330","dateFinished":"2019-07-29T08:54:14+0800","dateStarted":"2019-07-29T08:54:14+0800"},{"text":"%md\n**Stop Druid Ingestion**","user":"admin","dateUpdated":"2019-07-29T08:49:36+0800","config":{"tableHide":false,"editorSetting":{"language":"markdown","editOnDblClick":true,"completionSupport":false},"colWidth":12,"editorMode":"ace/mode/markdown","fontSize":9,"editorHide":true,"results":{},"enabled":true},"settings":{"params":{},"forms":{}},"results":{"code":"SUCCESS","msg":[{"type":"HTML","data":"<p><strong>Stop Druid Ingestion</strong></p>\n"}]},"apps":[],"jobName":"paragraph_1564269838511_-1081048352","id":"20190727-101938_363509403","dateCreated":"2019-07-28T07:23:58+0800","status":"FINISHED","progressUpdateIntervalMs":500,"$$hashKey":"object:331","dateFinished":"2019-07-29T08:49:36+0800","dateStarted":"2019-07-29T08:49:36+0800"},{"text":"ALTER TABLE workshop.clickstream_events SET TBLPROPERTIES('druid.kafka.ingestion' = 'STOP')\n","user":"admin","dateUpdated":"2019-07-28T07:23:58+0800","config":{"tableHide":true,"editorSetting":{"language":"sql","editOnDblClick":false,"completionSupport":true,"completionKey":"TAB"},"colWidth":12,"editorMode":"ace/mode/sql","fontSize":9,"editorHide":false,"results":{},"enabled":true},"settings":{"params":{},"forms":{}},"results":{"code":"SUCCESS","msg":[{"type":"TEXT","data":"Query executed successfully. Affected rows : -1"}]},"apps":[],"jobName":"paragraph_1564269838511_861929917","id":"20190727-102008_746547276","dateCreated":"2019-07-28T07:23:58+0800","status":"READY","errorMessage":"","progressUpdateIntervalMs":500,"$$hashKey":"object:332"},{"text":"%md\n### Other Tests","user":"admin","dateUpdated":"2019-07-29T08:49:46+0800","config":{"tableHide":false,"editorSetting":{"language":"markdown","editOnDblClick":true,"completionSupport":false},"colWidth":12,"editorMode":"ace/mode/markdown","fontSize":9,"editorHide":true,"results":{},"enabled":true},"settings":{"params":{},"forms":{}},"results":{"code":"SUCCESS","msg":[{"type":"HTML","data":"<h3>Other Tests</h3>\n"}]},"apps":[],"jobName":"paragraph_1564269838511_-2103670902","id":"20190727-102427_2077069272","dateCreated":"2019-07-28T07:23:58+0800","status":"FINISHED","progressUpdateIntervalMs":500,"$$hashKey":"object:333","dateFinished":"2019-07-29T08:49:46+0800","dateStarted":"2019-07-29T08:49:46+0800"},{"text":"%md\n**Validate Druid DS is populating and can be queried from Hive**","user":"admin","dateUpdated":"2019-07-29T08:49:52+0800","config":{"tableHide":false,"editorSetting":{"language":"markdown","editOnDblClick":true,"completionSupport":false},"colWidth":12,"editorMode":"ace/mode/markdown","fontSize":9,"editorHide":true,"results":{},"enabled":true},"settings":{"params":{},"forms":{}},"results":{"code":"SUCCESS","msg":[{"type":"HTML","data":"<p><strong>Validate Druid DS is populating and can be queried from Hive</strong></p>\n"}]},"apps":[],"jobName":"paragraph_1564269838511_-1721184593","id":"20190727-102528_984745387","dateCreated":"2019-07-28T07:23:58+0800","status":"FINISHED","progressUpdateIntervalMs":500,"$$hashKey":"object:334","dateFinished":"2019-07-29T08:49:52+0800","dateStarted":"2019-07-29T08:49:52+0800"},{"text":"select count(*) from clickstream_events","user":"admin","dateUpdated":"2019-07-29T08:55:17+0800","config":{"tableHide":false,"editorSetting":{"language":"sql","editOnDblClick":false,"completionSupport":true,"completionKey":"TAB"},"colWidth":12,"editorMode":"ace/mode/sql","fontSize":9,"editorHide":false,"results":{"0":{"graph":{"mode":"table","height":300,"optionOpen":false,"setting":{"table":{"tableGridState":{},"tableColumnTypeState":{"names":{"$f0":"string"},"updated":false},"tableOptionSpecHash":"[{\"name\":\"useFilter\",\"valueType\":\"boolean\",\"defaultValue\":false,\"widget\":\"checkbox\",\"description\":\"Enable filter for columns\"},{\"name\":\"showPagination\",\"valueType\":\"boolean\",\"defaultValue\":false,\"widget\":\"checkbox\",\"description\":\"Enable pagination for better navigation\"},{\"name\":\"showAggregationFooter\",\"valueType\":\"boolean\",\"defaultValue\":false,\"widget\":\"checkbox\",\"description\":\"Enable a footer for displaying aggregated values\"}]","tableOptionValue":{"useFilter":false,"showPagination":false,"showAggregationFooter":false},"updated":false,"initialized":false}},"commonSetting":{}}}},"enabled":true},"settings":{"params":{},"forms":{}},"results":{"code":"SUCCESS","msg":[{"type":"TABLE","data":"$f0\n6386\n"}]},"apps":[],"jobName":"paragraph_1564269838511_-387788362","id":"20190727-102045_718399695","dateCreated":"2019-07-28T07:23:58+0800","status":"FINISHED","progressUpdateIntervalMs":500,"$$hashKey":"object:335","dateFinished":"2019-07-29T08:55:17+0800","dateStarted":"2019-07-29T08:55:17+0800"},{"user":"admin","dateUpdated":"2019-07-29T08:50:58+0800","config":{"tableHide":false,"editorSetting":{"language":"sql","editOnDblClick":false,"completionSupport":true,"completionKey":"TAB"},"colWidth":12,"editorMode":"ace/mode/sql","fontSize":9,"editorHide":false,"results":{"0":{"graph":{"mode":"table","height":300,"optionOpen":false,"setting":{"table":{"tableGridState":{},"tableColumnTypeState":{"names":{"database_name":"string"},"updated":false},"tableOptionSpecHash":"[{\"name\":\"useFilter\",\"valueType\":\"boolean\",\"defaultValue\":false,\"widget\":\"checkbox\",\"description\":\"Enable filter for columns\"},{\"name\":\"showPagination\",\"valueType\":\"boolean\",\"defaultValue\":false,\"widget\":\"checkbox\",\"description\":\"Enable pagination for better navigation\"},{\"name\":\"showAggregationFooter\",\"valueType\":\"boolean\",\"defaultValue\":false,\"widget\":\"checkbox\",\"description\":\"Enable a footer for displaying aggregated values\"}]","tableOptionValue":{"useFilter":false,"showPagination":false,"showAggregationFooter":false},"updated":false,"initialized":false}},"commonSetting":{}}}},"enabled":true},"settings":{"params":{},"forms":{}},"apps":[],"jobName":"paragraph_1564269838512_482811975","id":"20190727-102517_1099623409","dateCreated":"2019-07-28T07:23:58+0800","status":"FINISHED","progressUpdateIntervalMs":500,"$$hashKey":"object:336","text":"use workshop","dateFinished":"2019-07-29T08:50:58+0800","dateStarted":"2019-07-29T08:50:58+0800","results":{"code":"SUCCESS","msg":[{"type":"TEXT","data":"Query executed successfully. Affected rows : -1"}]}},{"user":"admin","config":{"colWidth":12,"fontSize":9,"enabled":true,"results":{"0":{"graph":{"mode":"table","height":300,"optionOpen":false,"setting":{"table":{"tableGridState":{},"tableColumnTypeState":{"names":{"tab_name":"string"},"updated":false},"tableOptionSpecHash":"[{\"name\":\"useFilter\",\"valueType\":\"boolean\",\"defaultValue\":false,\"widget\":\"checkbox\",\"description\":\"Enable filter for columns\"},{\"name\":\"showPagination\",\"valueType\":\"boolean\",\"defaultValue\":false,\"widget\":\"checkbox\",\"description\":\"Enable pagination for better navigation\"},{\"name\":\"showAggregationFooter\",\"valueType\":\"boolean\",\"defaultValue\":false,\"widget\":\"checkbox\",\"description\":\"Enable a footer for displaying aggregated values\"}]","tableOptionValue":{"useFilter":false,"showPagination":false,"showAggregationFooter":false},"updated":false,"initialized":false}},"commonSetting":{}}}},"editorSetting":{"language":"sql","editOnDblClick":false,"completionSupport":true},"editorMode":"ace/mode/sql"},"settings":{"params":{},"forms":{}},"apps":[],"jobName":"paragraph_1564361436550_1991690132","id":"20190729-085036_1137435770","dateCreated":"2019-07-29T08:50:36+0800","status":"FINISHED","progressUpdateIntervalMs":500,"focus":true,"$$hashKey":"object:11010","text":"show tables","dateUpdated":"2019-07-29T08:51:16+0800","dateFinished":"2019-07-29T08:51:14+0800","dateStarted":"2019-07-29T08:51:14+0800","results":{"code":"SUCCESS","msg":[{"type":"TABLE","data":"tab_name\nclickstream_events\nproducts\nproducts_orc\nusers\nusers_orc\n"}]}},{"user":"admin","config":{"colWidth":12,"fontSize":9,"enabled":true,"results":{"0":{"graph":{"mode":"table","height":300,"optionOpen":false,"setting":{"table":{"tableGridState":{},"tableColumnTypeState":{"names":{"clickstream_events.__time":"string","clickstream_events.clickstream_id":"string","clickstream_events.user_session_id":"string","clickstream_events.ipaddress":"string","clickstream_events.ts":"string","clickstream_events.gender":"string","clickstream_events.bday":"string","clickstream_events.is_purchased":"string","clickstream_events.is_page_errored":"string","clickstream_events.url":"string","clickstream_events.city":"string","clickstream_events.state":"string","clickstream_events.country":"string"},"updated":false},"tableOptionSpecHash":"[{\"name\":\"useFilter\",\"valueType\":\"boolean\",\"defaultValue\":false,\"widget\":\"checkbox\",\"description\":\"Enable filter for columns\"},{\"name\":\"showPagination\",\"valueType\":\"boolean\",\"defaultValue\":false,\"widget\":\"checkbox\",\"description\":\"Enable pagination for better navigation\"},{\"name\":\"showAggregationFooter\",\"valueType\":\"boolean\",\"defaultValue\":false,\"widget\":\"checkbox\",\"description\":\"Enable a footer for displaying aggregated values\"}]","tableOptionValue":{"useFilter":false,"showPagination":false,"showAggregationFooter":false},"updated":false,"initialized":false}},"commonSetting":{}}}},"editorSetting":{"language":"sql","editOnDblClick":false,"completionSupport":true},"editorMode":"ace/mode/sql"},"settings":{"params":{},"forms":{}},"apps":[],"jobName":"paragraph_1564361474923_-895323085","id":"20190729-085114_478207913","dateCreated":"2019-07-29T08:51:14+0800","status":"FINISHED","progressUpdateIntervalMs":500,"focus":true,"$$hashKey":"object:11792","text":"select * from clickstream_events limit 10","dateUpdated":"2019-07-29T08:51:35+0800","dateFinished":"2019-07-29T08:51:34+0800","dateStarted":"2019-07-29T08:51:34+0800","results":{"code":"SUCCESS","msg":[{"type":"TABLE","data":"clickstream_events.__time\tclickstream_events.clickstream_id\tclickstream_events.user_session_id\tclickstream_events.ipaddress\tclickstream_events.ts\tclickstream_events.gender\tclickstream_events.bday\tclickstream_events.is_purchased\tclickstream_events.is_page_errored\tclickstream_events.url\tclickstream_events.city\tclickstream_events.state\tclickstream_events.country\n"}]}},{"user":"admin","config":{"colWidth":12,"fontSize":9,"enabled":true,"results":{},"editorSetting":{"language":"sql","editOnDblClick":false,"completionSupport":true},"editorMode":"ace/mode/sql"},"settings":{"params":{},"forms":{}},"apps":[],"jobName":"paragraph_1564361494084_-961183350","id":"20190729-085134_1244518795","dateCreated":"2019-07-29T08:51:34+0800","status":"READY","progressUpdateIntervalMs":500,"focus":true,"$$hashKey":"object:12217"}],"name":"Workshop-Solution","id":"2EK7QF28R","noteParams":{},"noteForms":{},"angularObjects":{"md:shared_process":[],"sh:shared_process":[],"spark2:shared_process":[]},"config":{"isZeppelinNotebookCronEnable":false,"looknfeel":"default","personalizedMode":"false"},"info":{}}